vllm_tgis_adapter/__init__.py
vllm_tgis_adapter/__main__.py
vllm_tgis_adapter/_version.py
vllm_tgis_adapter/healthcheck.py
vllm_tgis_adapter/http.py
vllm_tgis_adapter/logging.py
vllm_tgis_adapter/utils.py
vllm_tgis_adapter/grpc/__init__.py
vllm_tgis_adapter/grpc/adapters.py
vllm_tgis_adapter/grpc/grpc_server.py
vllm_tgis_adapter/grpc/validation.py
vllm_tgis_adapter/grpc/pb/.gitignore
vllm_tgis_adapter/grpc/pb/__init__.py
vllm_tgis_adapter/grpc/pb/generation.proto
vllm_tgis_adapter/grpc/pb/generation_pb2.py
vllm_tgis_adapter/grpc/pb/generation_pb2.pyi
vllm_tgis_adapter/grpc/pb/generation_pb2_grpc.py
vllm_tgis_adapter/tgis_utils/__init__.py
vllm_tgis_adapter/tgis_utils/args.py
vllm_tgis_adapter/tgis_utils/hub.py
vllm_tgis_adapter/tgis_utils/logits_processors.py
vllm_tgis_adapter/tgis_utils/logs.py
vllm_tgis_adapter/tgis_utils/scripts.py
vllm_tgis_adapter/tgis_utils/structured_outputs.py
vllm_tgis_adapter-0.10.0.dist-info/licenses/LICENSE
vllm_tgis_adapter-0.10.0.dist-info/METADATA
vllm_tgis_adapter-0.10.0.dist-info/WHEEL
vllm_tgis_adapter-0.10.0.dist-info/entry_points.txt
vllm_tgis_adapter-0.10.0.dist-info/top_level.txt
vllm_tgis_adapter-0.10.0.dist-info/RECORD
