Metadata-Version: 2.4
Name: vllm-tgis-adapter
Version: 0.10.0
Summary: vLLM adapter for a TGIS-compatible grpc server
Author-email: Daniele Trifirò <dtrifiro@redhat.com>
License: Apache 2
Project-URL: Issues, https://github.com/opendatahub-io/vllm-tgis-adapter/issues
Project-URL: Source, https://github.com/opendatahub-io/vllm-tgis-adapter
Classifier: Programming Language :: Python :: 3
Classifier: Programming Language :: Python :: 3.9
Classifier: Programming Language :: Python :: 3.10
Classifier: Programming Language :: Python :: 3.11
Classifier: Programming Language :: Python :: 3.12
Classifier: Development Status :: 4 - Beta
Requires-Python: >=3.9
License-File: LICENSE
Requires-Dist: vllm>=0.10.0
Requires-Dist: prometheus_client==0.21.1
Requires-Dist: grpcio==1.75.1
Requires-Dist: grpcio-health-checking==1.75.1
Requires-Dist: grpcio-reflection==1.75.1
Requires-Dist: accelerate==1.7.0
Requires-Dist: hf-transfer==0.1.9
Requires-Dist: cachetools~=5.5
Requires-Dist: protobuf==6.32.1; platform_machine == "s390x"
Provides-Extra: tests
Requires-Dist: pytest==8.3.5; extra == "tests"
Requires-Dist: pytest-cov==6.0.0; extra == "tests"
Requires-Dist: pytest-mock==3.14.0; extra == "tests"
Requires-Dist: pytest-asyncio==0.25.3; extra == "tests"
Requires-Dist: requests==2.32.3; extra == "tests"
Provides-Extra: dev
Requires-Dist: vllm_tgis_adapter[tests]; extra == "dev"
Requires-Dist: ruff==0.11.11; extra == "dev"
Requires-Dist: mypy==1.15.0; extra == "dev"
Requires-Dist: types-protobuf==5.28.0.20240924; extra == "dev"
Requires-Dist: types-requests==2.32.0.20250515; extra == "dev"
Provides-Extra: flash-attn
Requires-Dist: flash-attn==2.6.3; extra == "flash-attn"
Requires-Dist: packaging; extra == "flash-attn"
Requires-Dist: ninja; extra == "flash-attn"
Dynamic: license-file
